webget/Constants.py
webget/MetaExtractor.py
webget/Regex.py
webget/Validator.py
webget/WebScraper.py
webget/__init__.py
webget/webget.py
webget-1.0.dist-info/METADATA
webget-1.0.dist-info/WHEEL
webget-1.0.dist-info/top_level.txt
webget-1.0.dist-info/RECORD
