Metadata-Version: 2.1
Name: webget
Version: 1.0
Summary: Python website info api using meta data
Home-page: https://github.com/nepsho/webget
Author: BCrazyDreamer
Author-email: bcrazydreamer@gmail.com
License: MIT
Keywords: api,web,webget,scraping,website,website-info,python
Platform: UNKNOWN
Classifier: Development Status :: 5 - Production/Stable
Classifier: Intended Audience :: Developers
Classifier: License :: OSI Approved :: MIT License
Classifier: Programming Language :: Python
Classifier: Programming Language :: Python :: 3
Classifier: Operating System :: OS Independent
Requires-Dist: requests
